concurra/__init__.py
concurra/core.py
concurra-1.1.3.dist-info/licenses/LICENSE
concurra-1.1.3.dist-info/METADATA
concurra-1.1.3.dist-info/WHEEL
concurra-1.1.3.dist-info/top_level.txt
concurra-1.1.3.dist-info/RECORD
